cs/ansi_colour.py
cs_ansi_colour-20250306.dist-info/WHEEL
cs_ansi_colour-20250306.dist-info/METADATA
cs_ansi_colour-20250306.dist-info/RECORD
